MANIFEST.in
README.md
requirements.txt
setup.cfg
setup.py
wutil/__init__.py
wutil.egg-info/PKG-INFO
wutil.egg-info/SOURCES.txt
wutil.egg-info/dependency_links.txt
wutil.egg-info/requires.txt
wutil.egg-info/top_level.txt
wutil.egg-info/zip-safe
wutil/draw/__init__.py
wutil/draw/draw.py
wutil/im/__init__.py
wutil/im/channel_ops.py
wutil/im/resize.py
wutil/log/__init__.py
wutil/log/log.py
wutil/net/__init__.py
wutil/net/socket_util.py
wutil/obj_det/__init__.py
wutil/obj_det/bounding_box.py
wutil/path/__init__.py
wutil/path/path.py
wutil/video/__init__.py
wutil/video/common.py
wutil/video/reader.py
wutil/video/writer.py