Metadata-Version: 1.0
Name: wutil
Version: 0.0.9
Summary: Various utils
Home-page: UNKNOWN
Author: Red Pandas Team
Author-email: param3456@gmail.com
License: BSD
Platform: UNKNOWN
